{
"meta":{"test_sets":[],"test_metrics":[],"learn_metrics":[{"best_value":"Min","name":"RMSE"}],"launch_mode":"Train","parameters":"","iteration_count":500,"learn_sets":["learn"],"name":"experiment"},
"iterations":[
{"learn":[12.11128047],"iteration":0,"passed_time":0.003063877324,"remaining_time":1.528874785},
{"learn":[12.05056811],"iteration":1,"passed_time":0.004878321717,"remaining_time":1.214702108},
{"learn":[11.98418453],"iteration":2,"passed_time":0.00648692966,"remaining_time":1.074668014},
{"learn":[11.92444284],"iteration":3,"passed_time":0.008052043052,"remaining_time":0.9984533385},
{"learn":[11.86405215],"iteration":4,"passed_time":0.0103620911,"remaining_time":1.025847019},
{"learn":[11.80666968],"iteration":5,"passed_time":0.01249607524,"remaining_time":1.028843528},
{"learn":[11.74379522],"iteration":6,"passed_time":0.01410552807,"remaining_time":0.9934321913},
{"learn":[11.68284451],"iteration":7,"passed_time":0.01670615831,"remaining_time":1.027428736},
{"learn":[11.61948157],"iteration":8,"passed_time":0.01836629559,"remaining_time":1.001983459},
{"learn":[11.55613082],"iteration":9,"passed_time":0.0199951128,"remaining_time":0.979760527},
{"learn":[11.50023939],"iteration":10,"passed_time":0.02154317085,"remaining_time":0.9576918679},
{"learn":[11.44266518],"iteration":11,"passed_time":0.02308805504,"remaining_time":0.9389142385},
{"learn":[11.38670271],"iteration":12,"passed_time":0.02508492059,"remaining_time":0.9397197175},
{"learn":[11.33415602],"iteration":13,"passed_time":0.02682623017,"remaining_time":0.9312534189},
{"learn":[11.27668092],"iteration":14,"passed_time":0.02908601509,"remaining_time":0.9404478211},
{"learn":[11.21957132],"iteration":15,"passed_time":0.03151414488,"remaining_time":0.9533028827},
{"learn":[11.16303309],"iteration":16,"passed_time":0.03334070397,"remaining_time":0.9472682362},
{"learn":[11.11159916],"iteration":17,"passed_time":0.03497649317,"remaining_time":0.9365927616},
{"learn":[11.05301689],"iteration":18,"passed_time":0.03654806755,"remaining_time":0.9252431837},
{"learn":[10.99860837],"iteration":19,"passed_time":0.03820612727,"remaining_time":0.9169470544},
{"learn":[10.94310067],"iteration":20,"passed_time":0.03995068139,"remaining_time":0.9112560183},
{"learn":[10.89059247],"iteration":21,"passed_time":0.04148842868,"remaining_time":0.9014304051},
{"learn":[10.83962822],"iteration":22,"passed_time":0.04314410914,"remaining_time":0.8947713069},
{"learn":[10.78568045],"iteration":23,"passed_time":0.044614282,"remaining_time":0.8848499264},
{"learn":[10.73374985],"iteration":24,"passed_time":0.04692233812,"remaining_time":0.8915244243},
{"learn":[10.68237842],"iteration":25,"passed_time":0.04856555234,"remaining_time":0.8853873773},
{"learn":[10.63284247],"iteration":26,"passed_time":0.05014661072,"remaining_time":0.8784943285},
{"learn":[10.58347583],"iteration":27,"passed_time":0.05224925441,"remaining_time":0.8807731457},
{"learn":[10.53872223],"iteration":28,"passed_time":0.05413534634,"remaining_time":0.8792326941},
{"learn":[10.49253608],"iteration":29,"passed_time":0.05587877652,"remaining_time":0.8754341655},
{"learn":[10.44417458],"iteration":30,"passed_time":0.0573747281,"remaining_time":0.8680241122},
{"learn":[10.39572744],"iteration":31,"passed_time":0.05899674229,"remaining_time":0.862827356},
{"learn":[10.35279546],"iteration":32,"passed_time":0.06059914928,"remaining_time":0.8575697792},
{"learn":[10.30604092],"iteration":33,"passed_time":0.06312799788,"remaining_time":0.8652249122},
{"learn":[10.26318508],"iteration":34,"passed_time":0.0652413365,"remaining_time":0.8667777563},
{"learn":[10.22275307],"iteration":35,"passed_time":0.06714340558,"remaining_time":0.8654038942},
{"learn":[10.17826822],"iteration":36,"passed_time":0.06857951308,"remaining_time":0.8581706637},
{"learn":[10.13537633],"iteration":37,"passed_time":0.07014399315,"remaining_time":0.8528032851},
{"learn":[10.09485552],"iteration":38,"passed_time":0.07171882384,"remaining_time":0.8477532767},
{"learn":[10.05358681],"iteration":39,"passed_time":0.07350189698,"remaining_time":0.8452718153},
{"learn":[10.01173274],"iteration":40,"passed_time":0.07540321495,"remaining_time":0.8441481869},
{"learn":[9.972952671],"iteration":41,"passed_time":0.07738515799,"remaining_time":0.8438667228},
{"learn":[9.931119685],"iteration":42,"passed_time":0.07915039342,"remaining_time":0.8412030185},
{"learn":[9.894436276],"iteration":43,"passed_time":0.08062731902,"remaining_time":0.8355922153},
{"learn":[9.852510795],"iteration":44,"passed_time":0.08225275171,"remaining_time":0.8316667118},
{"learn":[9.81267168],"iteration":45,"passed_time":0.08393537604,"remaining_time":0.8284056679},
{"learn":[9.775445293],"iteration":46,"passed_time":0.08540957264,"remaining_time":0.8232029023},
{"learn":[9.737111917],"iteration":47,"passed_time":0.0869404227,"remaining_time":0.8186889804},
{"learn":[9.704415893],"iteration":48,"passed_time":0.08894774895,"remaining_time":0.8186823424},
{"learn":[9.667585092],"iteration":49,"passed_time":0.09078685944,"remaining_time":0.8170817349},
{"learn":[9.62977374],"iteration":50,"passed_time":0.0929878472,"remaining_time":0.8186577136},
{"learn":[9.594643355],"iteration":51,"passed_time":0.09491087258,"remaining_time":0.8176936715},
{"learn":[9.55637474],"iteration":52,"passed_time":0.0964140136,"remaining_time":0.8131521525},
{"learn":[9.520353493],"iteration":53,"passed_time":0.0979500657,"remaining_time":0.808994987},
{"learn":[9.486621743],"iteration":54,"passed_time":0.09959778476,"remaining_time":0.8058366221},
{"learn":[9.451334525],"iteration":55,"passed_time":0.101133903,"remaining_time":0.8018473737},
{"learn":[9.417642941],"iteration":56,"passed_time":0.1027653051,"remaining_time":0.7986847399},
{"learn":[9.383615502],"iteration":57,"passed_time":0.1042790659,"remaining_time":0.7946783986},
{"learn":[9.350945041],"iteration":58,"passed_time":0.1057229889,"remaining_time":0.7902345441},
{"learn":[9.317081475],"iteration":59,"passed_time":0.1071881124,"remaining_time":0.7860461575},
{"learn":[9.285209132],"iteration":60,"passed_time":0.1094435981,"remaining_time":0.7876350751},
{"learn":[9.25470366],"iteration":61,"passed_time":0.1109486971,"remaining_time":0.7837988602},
{"learn":[9.222420503],"iteration":62,"passed_time":0.1125343727,"remaining_time":0.7805955692},
{"learn":[9.189826909],"iteration":63,"passed_time":0.1141342663,"remaining_time":0.7775396892},
{"learn":[9.156525451],"iteration":64,"passed_time":0.1157189643,"remaining_time":0.7744269146},
{"learn":[9.123659334],"iteration":65,"passed_time":0.1172971745,"remaining_time":0.7713177837},
{"learn":[9.09268066],"iteration":66,"passed_time":0.1188716781,"remaining_time":0.7682303972},
{"learn":[9.061868833],"iteration":67,"passed_time":0.1203583319,"remaining_time":0.7646294024},
{"learn":[9.029803324],"iteration":68,"passed_time":0.1219627566,"remaining_time":0.7618253348},
{"learn":[9.002291971],"iteration":69,"passed_time":0.1235427363,"remaining_time":0.7589053804},
{"learn":[8.973733563],"iteration":70,"passed_time":0.1256775812,"remaining_time":0.7593758077},
{"learn":[8.946401991],"iteration":71,"passed_time":0.1271449617,"remaining_time":0.755806161},
{"learn":[8.917896824],"iteration":72,"passed_time":0.1286244976,"remaining_time":0.7523652119},
{"learn":[8.888256527],"iteration":73,"passed_time":0.1302183321,"remaining_time":0.7496352629},
{"learn":[8.861828895],"iteration":74,"passed_time":0.1324461808,"remaining_time":0.7505283578},
{"learn":[8.837421711],"iteration":75,"passed_time":0.1341392269,"remaining_time":0.7483556868},
{"learn":[8.809269259],"iteration":76,"passed_time":0.1357669555,"remaining_time":0.7458366515},
{"learn":[8.782360941],"iteration":77,"passed_time":0.1372768411,"remaining_time":0.7427029094},
{"learn":[8.754904962],"iteration":78,"passed_time":0.139069714,"remaining_time":0.7411183491},
{"learn":[8.730116482],"iteration":79,"passed_time":0.1410789443,"remaining_time":0.7406644574},
{"learn":[8.705350564],"iteration":80,"passed_time":0.1425984276,"remaining_time":0.7376387796},
{"learn":[8.679062027],"iteration":81,"passed_time":0.1441362664,"remaining_time":0.7347434066},
{"learn":[8.653232526],"iteration":82,"passed_time":0.1456621237,"remaining_time":0.7318205491},
{"learn":[8.624989953],"iteration":83,"passed_time":0.1471978279,"remaining_time":0.7289797189},
{"learn":[8.598505744],"iteration":84,"passed_time":0.1487360889,"remaining_time":0.726182081},
{"learn":[8.574443262],"iteration":85,"passed_time":0.1507398073,"remaining_time":0.7256544211},
{"learn":[8.550451636],"iteration":86,"passed_time":0.1522754036,"remaining_time":0.7228705942},
{"learn":[8.526144282],"iteration":87,"passed_time":0.1537288147,"remaining_time":0.7197303598},
{"learn":[8.500908863],"iteration":88,"passed_time":0.1561479937,"remaining_time":0.7210879261},
{"learn":[8.476754749],"iteration":89,"passed_time":0.1585574083,"remaining_time":0.7223170823},
{"learn":[8.454947362],"iteration":90,"passed_time":0.1607524253,"remaining_time":0.7225026586},
{"learn":[8.432945861],"iteration":91,"passed_time":0.1629841999,"remaining_time":0.7227994951},
{"learn":[8.40934386],"iteration":92,"passed_time":0.1650270801,"remaining_time":0.7222152862},
{"learn":[8.383370774],"iteration":93,"passed_time":0.167379,"remaining_time":0.7229348299},
{"learn":[8.361942188],"iteration":94,"passed_time":0.1690117621,"remaining_time":0.720523828},
{"learn":[8.341915062],"iteration":95,"passed_time":0.1709838189,"remaining_time":0.7195569045},
{"learn":[8.321267477],"iteration":96,"passed_time":0.1748318675,"remaining_time":0.7263633257},
{"learn":[8.299527304],"iteration":97,"passed_time":0.1771056743,"remaining_time":0.7264947048},
{"learn":[8.277756551],"iteration":98,"passed_time":0.1791919159,"remaining_time":0.7258177604},
{"learn":[8.257663032],"iteration":99,"passed_time":0.1814373641,"remaining_time":0.7257494563},
{"learn":[8.23480154],"iteration":100,"passed_time":0.1839121559,"remaining_time":0.7265440616},
{"learn":[8.213824757],"iteration":101,"passed_time":0.1855855649,"remaining_time":0.7241475964},
{"learn":[8.19142696],"iteration":102,"passed_time":0.1894364345,"remaining_time":0.7301579076},
{"learn":[8.170478116],"iteration":103,"passed_time":0.192498964,"remaining_time":0.7329768247},
{"learn":[8.1502751],"iteration":104,"passed_time":0.194755817,"remaining_time":0.7326528354},
{"learn":[8.12999954],"iteration":105,"passed_time":0.1969511085,"remaining_time":0.7320635542},
{"learn":[8.109992852],"iteration":106,"passed_time":0.1992891827,"remaining_time":0.7319686803},
{"learn":[8.091465113],"iteration":107,"passed_time":0.2013716511,"remaining_time":0.7309045114},
{"learn":[8.072221083],"iteration":108,"passed_time":0.2054312899,"remaining_time":0.7369140768},
{"learn":[8.053941847],"iteration":109,"passed_time":0.2078688285,"remaining_time":0.736989483},
{"learn":[8.035101006],"iteration":110,"passed_time":0.2103120435,"remaining_time":0.7370395037},
{"learn":[8.017831667],"iteration":111,"passed_time":0.2124206086,"remaining_time":0.7358856798},
{"learn":[7.995687579],"iteration":112,"passed_time":0.2146309291,"remaining_time":0.7350634473},
{"learn":[7.977490694],"iteration":113,"passed_time":0.2170408954,"remaining_time":0.7348928565},
{"learn":[7.959415945],"iteration":114,"passed_time":0.2214368281,"remaining_time":0.7413319898},
{"learn":[7.942655423],"iteration":115,"passed_time":0.2240777301,"remaining_time":0.7417745549},
{"learn":[7.923502241],"iteration":116,"passed_time":0.2261736211,"remaining_time":0.7403803152},
{"learn":[7.903936094],"iteration":117,"passed_time":0.2282592629,"remaining_time":0.7389410036},
{"learn":[7.886201697],"iteration":118,"passed_time":0.2305836984,"remaining_time":0.7382553706},
{"learn":[7.868168607],"iteration":119,"passed_time":0.2326579658,"remaining_time":0.736750225},
{"learn":[7.84985087],"iteration":120,"passed_time":0.237004767,"remaining_time":0.7423537743},
{"learn":[7.833810786],"iteration":121,"passed_time":0.2393877836,"remaining_time":0.7417096902},
{"learn":[7.816798747],"iteration":122,"passed_time":0.241030581,"remaining_time":0.7387685289},
{"learn":[7.798252536],"iteration":123,"passed_time":0.2428090347,"remaining_time":0.7362596537},
{"learn":[7.783136367],"iteration":124,"passed_time":0.2443500084,"remaining_time":0.7330500253},
{"learn":[7.769360515],"iteration":125,"passed_time":0.2458257489,"remaining_time":0.7296732548},
{"learn":[7.754128894],"iteration":126,"passed_time":0.2474216551,"remaining_time":0.7266793491},
{"learn":[7.739322816],"iteration":127,"passed_time":0.2508727453,"remaining_time":0.7290989161},
{"learn":[7.72445983],"iteration":128,"passed_time":0.2536591147,"remaining_time":0.7295157483},
{"learn":[7.708884267],"iteration":129,"passed_time":0.2551777698,"remaining_time":0.7262751911},
{"learn":[7.692988976],"iteration":130,"passed_time":0.2566511048,"remaining_time":0.7229332646},
{"learn":[7.679777318],"iteration":131,"passed_time":0.2583425608,"remaining_time":0.7202277452},
{"learn":[7.664720072],"iteration":132,"passed_time":0.2599288379,"remaining_time":0.7172472445},
{"learn":[7.650040524],"iteration":133,"passed_time":0.2615665597,"remaining_time":0.7144280661},
{"learn":[7.635180141],"iteration":134,"passed_time":0.263059564,"remaining_time":0.7112351174},
{"learn":[7.619528109],"iteration":135,"passed_time":0.2662456392,"remaining_time":0.7125986225},
{"learn":[7.602485846],"iteration":136,"passed_time":0.2689052414,"remaining_time":0.7125007492},
{"learn":[7.58790377],"iteration":137,"passed_time":0.2710285157,"remaining_time":0.71095886},
{"learn":[7.575274338],"iteration":138,"passed_time":0.2727172871,"remaining_time":0.7082801484},
{"learn":[7.560640176],"iteration":139,"passed_time":0.2742628146,"remaining_time":0.7052472374},
{"learn":[7.547257679],"iteration":140,"passed_time":0.2758353856,"remaining_time":0.7023042796},
{"learn":[7.533983958],"iteration":141,"passed_time":0.2772674847,"remaining_time":0.6990264756},
{"learn":[7.519883445],"iteration":142,"passed_time":0.2787754862,"remaining_time":0.6959639761},
{"learn":[7.50815052],"iteration":143,"passed_time":0.281580385,"remaining_time":0.6961292852},
{"learn":[7.494809027],"iteration":144,"passed_time":0.2832062322,"remaining_time":0.6933669823},
{"learn":[7.483029941],"iteration":145,"passed_time":0.2847457218,"remaining_time":0.6904108598},
{"learn":[7.467429689],"iteration":146,"passed_time":0.2862484239,"remaining_time":0.6873856709},
{"learn":[7.451161363],"iteration":147,"passed_time":0.287777147,"remaining_time":0.6844429442},
{"learn":[7.439591691],"iteration":148,"passed_time":0.2893074358,"remaining_time":0.6815228856},
{"learn":[7.428963144],"iteration":149,"passed_time":0.2908759989,"remaining_time":0.6787106641},
{"learn":[7.415515037],"iteration":150,"passed_time":0.2923095677,"remaining_time":0.6756029081},
{"learn":[7.403753115],"iteration":151,"passed_time":0.2938821278,"remaining_time":0.6728353979},
{"learn":[7.391377751],"iteration":152,"passed_time":0.2960070633,"remaining_time":0.6713362809},
{"learn":[7.379815796],"iteration":153,"passed_time":0.2979213173,"remaining_time":0.6693556869},
{"learn":[7.368969951],"iteration":154,"passed_time":0.2994848719,"remaining_time":0.6665953599},
{"learn":[7.355191379],"iteration":155,"passed_time":0.3009532517,"remaining_time":0.6636405037},
{"learn":[7.344325687],"iteration":156,"passed_time":0.3024861471,"remaining_time":0.6608455316},
{"learn":[7.331866352],"iteration":157,"passed_time":0.3039920362,"remaining_time":0.6580080783},
{"learn":[7.318342723],"iteration":158,"passed_time":0.3054489437,"remaining_time":0.6550823257},
{"learn":[7.306363339],"iteration":159,"passed_time":0.306888148,"remaining_time":0.6521373145},
{"learn":[7.295768068],"iteration":160,"passed_time":0.3084958078,"remaining_time":0.6495657071},
{"learn":[7.284580383],"iteration":161,"passed_time":0.3100845367,"remaining_time":0.6469665025},
{"learn":[7.275360441],"iteration":162,"passed_time":0.3126292691,"remaining_time":0.646356219},
{"learn":[7.263293637],"iteration":163,"passed_time":0.3142312086,"remaining_time":0.6437907689},
{"learn":[7.252877647],"iteration":164,"passed_time":0.315660017,"remaining_time":0.6408854891},
{"learn":[7.24271474],"iteration":165,"passed_time":0.3171978327,"remaining_time":0.6382173261},
{"learn":[7.231454258],"iteration":166,"passed_time":0.3187235297,"remaining_time":0.6355385352},
{"learn":[7.222868809],"iteration":167,"passed_time":0.3201716821,"remaining_time":0.6327202289},
{"learn":[7.213582391],"iteration":168,"passed_time":0.3218490197,"remaining_time":0.6303670149},
{"learn":[7.202723816],"iteration":169,"passed_time":0.3233874121,"remaining_time":0.6277520352},
{"learn":[7.193173123],"iteration":170,"passed_time":0.3249779712,"remaining_time":0.6252500148},
{"learn":[7.183705236],"iteration":171,"passed_time":0.3273393624,"remaining_time":0.6242285515},
{"learn":[7.173869424],"iteration":172,"passed_time":0.3289411596,"remaining_time":0.6217558335},
{"learn":[7.164344267],"iteration":173,"passed_time":0.3304485436,"remaining_time":0.6191162369},
{"learn":[7.154655646],"iteration":174,"passed_time":0.3319293924,"remaining_time":0.6164403002},
{"learn":[7.144555343],"iteration":175,"passed_time":0.3334683302,"remaining_time":0.6138848806},
{"learn":[7.135006535],"iteration":176,"passed_time":0.3349830061,"remaining_time":0.6112966721},
{"learn":[7.126182329],"iteration":177,"passed_time":0.3366300057,"remaining_time":0.608959898},
{"learn":[7.115074264],"iteration":178,"passed_time":0.3381445873,"remaining_time":0.6063933661},
{"learn":[7.106353037],"iteration":179,"passed_time":0.3403433431,"remaining_time":0.6050548321},
{"learn":[7.095996815],"iteration":180,"passed_time":0.3422601299,"remaining_time":0.6032098422},
{"learn":[7.08708923],"iteration":181,"passed_time":0.3441299172,"remaining_time":0.6012819432},
{"learn":[7.078675818],"iteration":182,"passed_time":0.3458408453,"remaining_time":0.5990794971},
{"learn":[7.070109242],"iteration":183,"passed_time":0.3473239139,"remaining_time":0.5964910695},
{"learn":[7.059838467],"iteration":184,"passed_time":0.348912473,"remaining_time":0.5940942107},
{"learn":[7.05019172],"iteration":185,"passed_time":0.3504110602,"remaining_time":0.5915541554},
{"learn":[7.042318805],"iteration":186,"passed_time":0.3518815466,"remaining_time":0.5889782036},
{"learn":[7.034182287],"iteration":187,"passed_time":0.3533917493,"remaining_time":0.5864799243},
{"learn":[7.025417006],"iteration":188,"passed_time":0.3559047752,"remaining_time":0.5856422492},
{"learn":[7.017108077],"iteration":189,"passed_time":0.358120358,"remaining_time":0.5843016367},
{"learn":[7.007962613],"iteration":190,"passed_time":0.3603729915,"remaining_time":0.583011803},
{"learn":[6.998692777],"iteration":191,"passed_time":0.3624110398,"remaining_time":0.5813677097},
{"learn":[6.990700657],"iteration":192,"passed_time":0.3643486017,"remaining_time":0.5795596929},
{"learn":[6.982543655],"iteration":193,"passed_time":0.3658010769,"remaining_time":0.5769852037},
{"learn":[6.974491973],"iteration":194,"passed_time":0.3673302838,"remaining_time":0.5745422388},
{"learn":[6.966693486],"iteration":195,"passed_time":0.3688248306,"remaining_time":0.5720548393},
{"learn":[6.959487622],"iteration":196,"passed_time":0.3703989745,"remaining_time":0.5696999455},
{"learn":[6.950463639],"iteration":197,"passed_time":0.3718982358,"remaining_time":0.5672387234},
{"learn":[6.943458758],"iteration":198,"passed_time":0.3743057573,"remaining_time":0.5661609695},
{"learn":[6.933769636],"iteration":199,"passed_time":0.3759379875,"remaining_time":0.5639069813},
{"learn":[6.925134415],"iteration":200,"passed_time":0.377321126,"remaining_time":0.5612886402},
{"learn":[6.916956921],"iteration":201,"passed_time":0.3787404328,"remaining_time":0.5587358859},
{"learn":[6.90988307],"iteration":202,"passed_time":0.3802266054,"remaining_time":0.5562921271},
{"learn":[6.90225195],"iteration":203,"passed_time":0.3817439224,"remaining_time":0.5539029462},
{"learn":[6.894018125],"iteration":204,"passed_time":0.3833809189,"remaining_time":0.551694493},
{"learn":[6.885236228],"iteration":205,"passed_time":0.3850047343,"remaining_time":0.5494727761},
{"learn":[6.876413844],"iteration":206,"passed_time":0.38646623,"remaining_time":0.5470270792},
{"learn":[6.870029161],"iteration":207,"passed_time":0.3880596278,"remaining_time":0.5447760159},
{"learn":[6.861924952],"iteration":208,"passed_time":0.3900682415,"remaining_time":0.5431093697},
{"learn":[6.855860364],"iteration":209,"passed_time":0.3915349927,"remaining_time":0.5406911804},
{"learn":[6.846907554],"iteration":210,"passed_time":0.3930589265,"remaining_time":0.5383603306},
{"learn":[6.838687458],"iteration":211,"passed_time":0.394672244,"remaining_time":0.5361585202},
{"learn":[6.832438647],"iteration":212,"passed_time":0.396104412,"remaining_time":0.5337181514},
{"learn":[6.82224287],"iteration":213,"passed_time":0.3975953097,"remaining_time":0.5313656943},
{"learn":[6.813358767],"iteration":214,"passed_time":0.3990867284,"remaining_time":0.5290219423},
{"learn":[6.805633429],"iteration":215,"passed_time":0.4005956064,"remaining_time":0.5267090381},
{"learn":[6.798990388],"iteration":216,"passed_time":0.4021588688,"remaining_time":0.5244744694},
{"learn":[6.791570246],"iteration":217,"passed_time":0.4038900035,"remaining_time":0.5224632156},
{"learn":[6.78274931],"iteration":218,"passed_time":0.4059419596,"remaining_time":0.5208661673},
{"learn":[6.775664329],"iteration":219,"passed_time":0.4078072262,"remaining_time":0.5190273788},
{"learn":[6.768479442],"iteration":220,"passed_time":0.4093375394,"remaining_time":0.5167654909},
{"learn":[6.763958916],"iteration":221,"passed_time":0.4110364285,"remaining_time":0.5147212934},
{"learn":[6.7565624],"iteration":222,"passed_time":0.4126391721,"remaining_time":0.5125607654},
{"learn":[6.749361751],"iteration":223,"passed_time":0.4142074467,"remaining_time":0.5103627468},
{"learn":[6.742668745],"iteration":224,"passed_time":0.4157554114,"remaining_time":0.5081455028},
{"learn":[6.735866274],"iteration":225,"passed_time":0.4172685551,"remaining_time":0.5058919651},
{"learn":[6.729415694],"iteration":226,"passed_time":0.4187481762,"remaining_time":0.5036046348},
{"learn":[6.72390448],"iteration":227,"passed_time":0.4210560335,"remaining_time":0.502312461},
{"learn":[6.717833928],"iteration":228,"passed_time":0.4225206641,"remaining_time":0.500013537},
{"learn":[6.713487196],"iteration":229,"passed_time":0.4236926612,"remaining_time":0.4973783414},
{"learn":[6.707846597],"iteration":230,"passed_time":0.425194281,"remaining_time":0.4951396605},
{"learn":[6.702012794],"iteration":231,"passed_time":0.4266776757,"remaining_time":0.4928862806},
{"learn":[6.696646982],"iteration":232,"passed_time":0.4287058052,"remaining_time":0.4912637338},
{"learn":[6.688593415],"iteration":233,"passed_time":0.4303005266,"remaining_time":0.4891450431},
{"learn":[6.682893553],"iteration":234,"passed_time":0.431780724,"remaining_time":0.4869016674},
{"learn":[6.676268925],"iteration":235,"passed_time":0.4333997586,"remaining_time":0.484820069},
{"learn":[6.671129958],"iteration":236,"passed_time":0.4353900518,"remaining_time":0.4831543612},
{"learn":[6.664211725],"iteration":237,"passed_time":0.4371312658,"remaining_time":0.4812117295},
{"learn":[6.657423322],"iteration":238,"passed_time":0.4388115511,"remaining_time":0.4792042462},
{"learn":[6.65197428],"iteration":239,"passed_time":0.4404869616,"remaining_time":0.4771942084},
{"learn":[6.646292962],"iteration":240,"passed_time":0.4420038862,"remaining_time":0.4750166246},
{"learn":[6.641378208],"iteration":241,"passed_time":0.443546947,"remaining_time":0.472872365},
{"learn":[6.636236077],"iteration":242,"passed_time":0.4450752678,"remaining_time":0.4707174643},
{"learn":[6.630283647],"iteration":243,"passed_time":0.4466241005,"remaining_time":0.4685892202},
{"learn":[6.624526161],"iteration":244,"passed_time":0.448236493,"remaining_time":0.4665318601},
{"learn":[6.618265999],"iteration":245,"passed_time":0.4502353061,"remaining_time":0.4648771047},
{"learn":[6.61556082],"iteration":246,"passed_time":0.4516353812,"remaining_time":0.4626062812},
{"learn":[6.610110253],"iteration":247,"passed_time":0.4540885531,"remaining_time":0.461412562},
{"learn":[6.604379963],"iteration":248,"passed_time":0.4563593315,"remaining_time":0.4600248683},
{"learn":[6.599607193],"iteration":249,"passed_time":0.4586958101,"remaining_time":0.4586958101},
{"learn":[6.593948044],"iteration":250,"passed_time":0.460813563,"remaining_time":0.4571417418},
{"learn":[6.588660581],"iteration":251,"passed_time":0.4631613124,"remaining_time":0.4558095455},
{"learn":[6.584120168],"iteration":252,"passed_time":0.4647654553,"remaining_time":0.4537433497},
{"learn":[6.577715715],"iteration":253,"passed_time":0.4673323609,"remaining_time":0.4526132314},
{"learn":[6.571585844],"iteration":254,"passed_time":0.4703606484,"remaining_time":0.4519151328},
{"learn":[6.567097651],"iteration":255,"passed_time":0.4727163945,"remaining_time":0.4505578135},
{"learn":[6.562151032],"iteration":256,"passed_time":0.4742777116,"remaining_time":0.4484415716},
{"learn":[6.557433778],"iteration":257,"passed_time":0.4759225186,"remaining_time":0.4464079438},
{"learn":[6.550939877],"iteration":258,"passed_time":0.4774947798,"remaining_time":0.4443098144},
{"learn":[6.545730547],"iteration":259,"passed_time":0.4789345848,"remaining_time":0.4420934629},
{"learn":[6.54119011],"iteration":260,"passed_time":0.4804196716,"remaining_time":0.4399245269},
{"learn":[6.535531197],"iteration":261,"passed_time":0.4833206919,"remaining_time":0.4390470408},
{"learn":[6.53071607],"iteration":262,"passed_time":0.4862704759,"remaining_time":0.4381981095},
{"learn":[6.525410525],"iteration":263,"passed_time":0.4885741178,"remaining_time":0.4367556508},
{"learn":[6.520550482],"iteration":264,"passed_time":0.4905152097,"remaining_time":0.4349851859},
{"learn":[6.514981237],"iteration":265,"passed_time":0.4927687637,"remaining_time":0.4334883109},
{"learn":[6.510428878],"iteration":266,"passed_time":0.4949071807,"remaining_time":0.4318852925},
{"learn":[6.505778026],"iteration":267,"passed_time":0.4965115021,"remaining_time":0.4298159272},
{"learn":[6.501082496],"iteration":268,"passed_time":0.4996172862,"remaining_time":0.4290393796},
{"learn":[6.497898047],"iteration":269,"passed_time":0.5027827476,"remaining_time":0.4282964146},
{"learn":[6.492658349],"iteration":270,"passed_time":0.5050706886,"remaining_time":0.4267940505},
{"learn":[6.488293242],"iteration":271,"passed_time":0.5072524067,"remaining_time":0.4251968703},
{"learn":[6.483104291],"iteration":272,"passed_time":0.5092637458,"remaining_time":0.4234537374},
{"learn":[6.478168071],"iteration":273,"passed_time":0.5113732519,"remaining_time":0.4217896165},
{"learn":[6.47365837],"iteration":274,"passed_time":0.5138860155,"remaining_time":0.4204521945},
{"learn":[6.468374642],"iteration":275,"passed_time":0.5180946978,"remaining_time":0.4204826533},
{"learn":[6.463801297],"iteration":276,"passed_time":0.5201056002,"remaining_time":0.4187131728},
{"learn":[6.459282913],"iteration":277,"passed_time":0.5218014166,"remaining_time":0.4166903398},
{"learn":[6.455263389],"iteration":278,"passed_time":0.52343501,"remaining_time":0.4146205634},
{"learn":[6.450249684],"iteration":279,"passed_time":0.524904159,"remaining_time":0.4124246964},
{"learn":[6.445396823],"iteration":280,"passed_time":0.5263821845,"remaining_time":0.4102409196},
{"learn":[6.441089213],"iteration":281,"passed_time":0.5278747539,"remaining_time":0.4080733913},
{"learn":[6.436266815],"iteration":282,"passed_time":0.5307885988,"remaining_time":0.407000445},
{"learn":[6.431525148],"iteration":283,"passed_time":0.5334827248,"remaining_time":0.4057474245},
{"learn":[6.428083296],"iteration":284,"passed_time":0.5358424267,"remaining_time":0.4042320061},
{"learn":[6.424057003],"iteration":285,"passed_time":0.538120559,"remaining_time":0.402649649},
{"learn":[6.4194101],"iteration":286,"passed_time":0.5396173197,"remaining_time":0.4004825404},
{"learn":[6.415537029],"iteration":287,"passed_time":0.5411573312,"remaining_time":0.3983519243},
{"learn":[6.410373394],"iteration":288,"passed_time":0.5427058744,"remaining_time":0.3962316246},
{"learn":[6.40597415],"iteration":289,"passed_time":0.5448981682,"remaining_time":0.3945814322},
{"learn":[6.400601457],"iteration":290,"passed_time":0.5475902811,"remaining_time":0.3932864905},
{"learn":[6.395946247],"iteration":291,"passed_time":0.5491101168,"remaining_time":0.3911469325},
{"learn":[6.392716872],"iteration":292,"passed_time":0.5506147003,"remaining_time":0.3890008292},
{"learn":[6.38873965],"iteration":293,"passed_time":0.5522046139,"remaining_time":0.3869188791},
{"learn":[6.384257617],"iteration":294,"passed_time":0.5536902529,"remaining_time":0.3847678028},
{"learn":[6.380022571],"iteration":295,"passed_time":0.5551699963,"remaining_time":0.3826171596},
{"learn":[6.37577014],"iteration":296,"passed_time":0.5567211281,"remaining_time":0.3805198283},
{"learn":[6.371471556],"iteration":297,"passed_time":0.5583253535,"remaining_time":0.3784621524},
{"learn":[6.36642787],"iteration":298,"passed_time":0.5603672063,"remaining_time":0.3767017005},
{"learn":[6.3621732],"iteration":299,"passed_time":0.5630893834,"remaining_time":0.3753929223},
{"learn":[6.358680582],"iteration":300,"passed_time":0.5651873818,"remaining_time":0.3736620897},
{"learn":[6.353857068],"iteration":301,"passed_time":0.5668705321,"remaining_time":0.3716568389},
{"learn":[6.350512148],"iteration":302,"passed_time":0.5682966188,"remaining_time":0.3694865805},
{"learn":[6.346260066],"iteration":303,"passed_time":0.5699189406,"remaining_time":0.367447738},
{"learn":[6.342955915],"iteration":304,"passed_time":0.5713650082,"remaining_time":0.3652989397},
{"learn":[6.339822438],"iteration":305,"passed_time":0.5729253921,"remaining_time":0.3632272094},
{"learn":[6.335543965],"iteration":306,"passed_time":0.574460607,"remaining_time":0.3611429874},
{"learn":[6.331902162],"iteration":307,"passed_time":0.5769983706,"remaining_time":0.3596872959},
{"learn":[6.327792955],"iteration":308,"passed_time":0.5785849508,"remaining_time":0.3576366525},
{"learn":[6.323641539],"iteration":309,"passed_time":0.5800794337,"remaining_time":0.3555325561},
{"learn":[6.319060244],"iteration":310,"passed_time":0.5815696274,"remaining_time":0.3534297736},
{"learn":[6.31533042],"iteration":311,"passed_time":0.5832106291,"remaining_time":0.3514217893},
{"learn":[6.311912637],"iteration":312,"passed_time":0.5847289454,"remaining_time":0.3493428523},
{"learn":[6.308095997],"iteration":313,"passed_time":0.586137627,"remaining_time":0.3472025434},
{"learn":[6.303872083],"iteration":314,"passed_time":0.5877334294,"remaining_time":0.345176776},
{"learn":[6.30014835],"iteration":315,"passed_time":0.5892174176,"remaining_time":0.3430886229},
{"learn":[6.297049571],"iteration":316,"passed_time":0.5908858442,"remaining_time":0.3411107555},
{"learn":[6.293500288],"iteration":317,"passed_time":0.5927818723,"remaining_time":0.3392650967},
{"learn":[6.28953405],"iteration":318,"passed_time":0.5942721611,"remaining_time":0.3371889064},
{"learn":[6.285993221],"iteration":319,"passed_time":0.5958612302,"remaining_time":0.335171942},
{"learn":[6.282992761],"iteration":320,"passed_time":0.597507776,"remaining_time":0.3331896944},
{"learn":[6.279676967],"iteration":321,"passed_time":0.5990444514,"remaining_time":0.3311487961},
{"learn":[6.276163142],"iteration":322,"passed_time":0.6006561453,"remaining_time":0.3291521292},
{"learn":[6.272797876],"iteration":323,"passed_time":0.6021656803,"remaining_time":0.3271023449},
{"learn":[6.2700422],"iteration":324,"passed_time":0.6037109265,"remaining_time":0.3250751142},
{"learn":[6.267594452],"iteration":325,"passed_time":0.6052586529,"remaining_time":0.3230521644},
{"learn":[6.264097584],"iteration":326,"passed_time":0.6075994221,"remaining_time":0.321451682},
{"learn":[6.260548927],"iteration":327,"passed_time":0.6092111749,"remaining_time":0.3194643966},
{"learn":[6.25773016],"iteration":328,"passed_time":0.6106663202,"remaining_time":0.3173979962},
{"learn":[6.251860798],"iteration":329,"passed_time":0.612132424,"remaining_time":0.3153409457},
{"learn":[6.249428718],"iteration":330,"passed_time":0.6136451673,"remaining_time":0.3133112788},
{"learn":[6.245803351],"iteration":331,"passed_time":0.6151209612,"remaining_time":0.3112660286},
{"learn":[6.241863024],"iteration":332,"passed_time":0.6167447014,"remaining_time":0.3092983938},
{"learn":[6.238229473],"iteration":333,"passed_time":0.6182811712,"remaining_time":0.3072894444},
{"learn":[6.235987628],"iteration":334,"passed_time":0.6198290852,"remaining_time":0.3052889524},
{"learn":[6.232664349],"iteration":335,"passed_time":0.6217253896,"remaining_time":0.3034612021},
{"learn":[6.228083353],"iteration":336,"passed_time":0.623510668,"remaining_time":0.3015793439},
{"learn":[6.22495784],"iteration":337,"passed_time":0.6250718977,"remaining_time":0.2995906729},
{"learn":[6.22175467],"iteration":338,"passed_time":0.6265897587,"remaining_time":0.2975839267},
{"learn":[6.218653279],"iteration":339,"passed_time":0.6280675605,"remaining_time":0.2955612049},
{"learn":[6.215525757],"iteration":340,"passed_time":0.6295153595,"remaining_time":0.2935276896},
{"learn":[6.212122904],"iteration":341,"passed_time":0.6310487723,"remaining_time":0.2915371521},
{"learn":[6.208752818],"iteration":342,"passed_time":0.6325371829,"remaining_time":0.2895286814},
{"learn":[6.204361162],"iteration":343,"passed_time":0.6340533931,"remaining_time":0.2875358411},
{"learn":[6.201070262],"iteration":344,"passed_time":0.6356751174,"remaining_time":0.2855931687},
{"learn":[6.197884016],"iteration":345,"passed_time":0.6381987318,"remaining_time":0.2840537708},
{"learn":[6.194364839],"iteration":346,"passed_time":0.6398159,"remaining_time":0.282109028},
{"learn":[6.191461162],"iteration":347,"passed_time":0.6413571908,"remaining_time":0.2801330259},
{"learn":[6.188588445],"iteration":348,"passed_time":0.6429051791,"remaining_time":0.2781624127},
{"learn":[6.185182919],"iteration":349,"passed_time":0.6447872097,"remaining_time":0.2763373756},
{"learn":[6.181698151],"iteration":350,"passed_time":0.6464824915,"remaining_time":0.2744327385},
{"learn":[6.178542752],"iteration":351,"passed_time":0.6481037958,"remaining_time":0.2724981869},
{"learn":[6.174895173],"iteration":352,"passed_time":0.649602219,"remaining_time":0.2705142385},
{"learn":[6.17165644],"iteration":353,"passed_time":0.6511919188,"remaining_time":0.2685706784},
{"learn":[6.168452138],"iteration":354,"passed_time":0.6537157855,"remaining_time":0.267010673},
{"learn":[6.1654321],"iteration":355,"passed_time":0.6558955619,"remaining_time":0.26530607},
{"learn":[6.162271341],"iteration":356,"passed_time":0.6580525061,"remaining_time":0.2635896593},
{"learn":[6.159491666],"iteration":357,"passed_time":0.6596678822,"remaining_time":0.2616559756},
{"learn":[6.156380597],"iteration":358,"passed_time":0.6611754936,"remaining_time":0.2596817398},
{"learn":[6.153751422],"iteration":359,"passed_time":0.6628304755,"remaining_time":0.2577674071},
{"learn":[6.150420528],"iteration":360,"passed_time":0.6644473148,"remaining_time":0.2558398248},
{"learn":[6.146972122],"iteration":361,"passed_time":0.6660583102,"remaining_time":0.2539117315},
{"learn":[6.143328823],"iteration":362,"passed_time":0.667690256,"remaining_time":0.2519932922},
{"learn":[6.140626679],"iteration":363,"passed_time":0.6698605271,"remaining_time":0.2502775596},
{"learn":[6.137927355],"iteration":364,"passed_time":0.6715272862,"remaining_time":0.2483731058},
{"learn":[6.134650084],"iteration":365,"passed_time":0.6731240395,"remaining_time":0.2464443205},
{"learn":[6.132205215],"iteration":366,"passed_time":0.6748112139,"remaining_time":0.244550113},
{"learn":[6.128881534],"iteration":367,"passed_time":0.676420534,"remaining_time":0.2426291046},
{"learn":[6.126352596],"iteration":368,"passed_time":0.6779811616,"remaining_time":0.2406924991},
{"learn":[6.12340309],"iteration":369,"passed_time":0.6799000591,"remaining_time":0.2388838045},
{"learn":[6.120626112],"iteration":370,"passed_time":0.6820059468,"remaining_time":0.2371395341},
{"learn":[6.117664851],"iteration":371,"passed_time":0.6838749051,"remaining_time":0.2353117953},
{"learn":[6.115240897],"iteration":372,"passed_time":0.6859390162,"remaining_time":0.2335502816},
{"learn":[6.11195324],"iteration":373,"passed_time":0.6874507111,"remaining_time":0.2316010417},
{"learn":[6.110048339],"iteration":374,"passed_time":0.6889617003,"remaining_time":0.2296539001},
{"learn":[6.106561704],"iteration":375,"passed_time":0.6906246644,"remaining_time":0.2277591978},
{"learn":[6.10388627],"iteration":376,"passed_time":0.6921294599,"remaining_time":0.2258141209},
{"learn":[6.101484203],"iteration":377,"passed_time":0.6937562145,"remaining_time":0.2239107359},
{"learn":[6.09874522],"iteration":378,"passed_time":0.6960314981,"remaining_time":0.2222158609},
{"learn":[6.095702907],"iteration":379,"passed_time":0.6978875561,"remaining_time":0.220385544},
{"learn":[6.093486321],"iteration":380,"passed_time":0.6999274501,"remaining_time":0.2186125107},
{"learn":[6.091065032],"iteration":381,"passed_time":0.7015602824,"remaining_time":0.2167123385},
{"learn":[6.088280614],"iteration":382,"passed_time":0.7030278921,"remaining_time":0.2147630897},
{"learn":[6.084835901],"iteration":383,"passed_time":0.7045227781,"remaining_time":0.2128245892},
{"learn":[6.082631874],"iteration":384,"passed_time":0.7061007428,"remaining_time":0.2109132089},
{"learn":[6.080008133],"iteration":385,"passed_time":0.707864419,"remaining_time":0.2090584035},
{"learn":[6.076992177],"iteration":386,"passed_time":0.7093846262,"remaining_time":0.2071329787},
{"learn":[6.074017213],"iteration":387,"passed_time":0.7109556923,"remaining_time":0.2052243235},
{"learn":[6.070357997],"iteration":388,"passed_time":0.7124759249,"remaining_time":0.2033028989},
{"learn":[6.068487687],"iteration":389,"passed_time":0.7146390922,"remaining_time":0.2015648722},
{"learn":[6.066390519],"iteration":390,"passed_time":0.7160857986,"remaining_time":0.1996249413},
{"learn":[6.064486478],"iteration":391,"passed_time":0.7177142878,"remaining_time":0.1977376099},
{"learn":[6.062299948],"iteration":392,"passed_time":0.7192374668,"remaining_time":0.1958229235},
{"learn":[6.060257077],"iteration":393,"passed_time":0.7207824081,"remaining_time":0.1939160793},
{"learn":[6.057069725],"iteration":394,"passed_time":0.7223777625,"remaining_time":0.1920244685},
{"learn":[6.054330812],"iteration":395,"passed_time":0.7244833875,"remaining_time":0.1902683644},
{"learn":[6.052232118],"iteration":396,"passed_time":0.7260089703,"remaining_time":0.1883600099},
{"learn":[6.049912998],"iteration":397,"passed_time":0.7276086791,"remaining_time":0.186472576},
{"learn":[6.047702745],"iteration":398,"passed_time":0.7301725041,"remaining_time":0.1848306339},
{"learn":[6.045331236],"iteration":399,"passed_time":0.7325608387,"remaining_time":0.1831402097},
{"learn":[6.043087514],"iteration":400,"passed_time":0.7347922532,"remaining_time":0.1814075637},
{"learn":[6.041280739],"iteration":401,"passed_time":0.7369548347,"remaining_time":0.1796556562},
{"learn":[6.038190744],"iteration":402,"passed_time":0.7395126744,"remaining_time":0.1779968472},
{"learn":[6.035798509],"iteration":403,"passed_time":0.7416003353,"remaining_time":0.1762218619},
{"learn":[6.03342837],"iteration":404,"passed_time":0.7430390133,"remaining_time":0.1742931019},
{"learn":[6.031253841],"iteration":405,"passed_time":0.7448533711,"remaining_time":0.1724537362},
{"learn":[6.029460743],"iteration":406,"passed_time":0.7484934033,"remaining_time":0.1710316622},
{"learn":[6.026943387],"iteration":407,"passed_time":0.750751667,"remaining_time":0.1692871406},
{"learn":[6.023990073],"iteration":408,"passed_time":0.7528847107,"remaining_time":0.1675122461},
{"learn":[6.020999202],"iteration":409,"passed_time":0.7550634447,"remaining_time":0.1657456342},
{"learn":[6.018812815],"iteration":410,"passed_time":0.7573703782,"remaining_time":0.1640047778},
{"learn":[6.016627435],"iteration":411,"passed_time":0.7596101002,"remaining_time":0.1622468175},
{"learn":[6.013918912],"iteration":412,"passed_time":0.7637038243,"remaining_time":0.1608770768},
{"learn":[6.011741057],"iteration":413,"passed_time":0.766093513,"remaining_time":0.1591401984},
{"learn":[6.009336533],"iteration":414,"passed_time":0.7682259809,"remaining_time":0.1573474901},
{"learn":[6.006341108],"iteration":415,"passed_time":0.7705971252,"remaining_time":0.1556013426},
{"learn":[6.004152415],"iteration":416,"passed_time":0.7722895425,"remaining_time":0.1537171032},
{"learn":[6.001464997],"iteration":417,"passed_time":0.773855417,"remaining_time":0.1518089574},
{"learn":[5.99943471],"iteration":418,"passed_time":0.7754249754,"remaining_time":0.1499031575},
{"learn":[5.997077338],"iteration":419,"passed_time":0.7797663036,"remaining_time":0.148526915},
{"learn":[5.994916123],"iteration":420,"passed_time":0.7817889438,"remaining_time":0.1467014883},
{"learn":[5.992031807],"iteration":421,"passed_time":0.7838782383,"remaining_time":0.1448874469},
{"learn":[5.989238849],"iteration":422,"passed_time":0.7853463554,"remaining_time":0.1429590292},
{"learn":[5.987602173],"iteration":423,"passed_time":0.7869022661,"remaining_time":0.1410485194},
{"learn":[5.985381622],"iteration":424,"passed_time":0.7883425813,"remaining_time":0.139119279},
{"learn":[5.98296217],"iteration":425,"passed_time":0.7898762985,"remaining_time":0.1372085589},
{"learn":[5.980584179],"iteration":426,"passed_time":0.7922409764,"remaining_time":0.1354416657},
{"learn":[5.977173208],"iteration":427,"passed_time":0.7952229579,"remaining_time":0.1337758247},
{"learn":[5.975113531],"iteration":428,"passed_time":0.7972835911,"remaining_time":0.1319513636},
{"learn":[5.972894292],"iteration":429,"passed_time":0.7995292282,"remaining_time":0.1301559209},
{"learn":[5.970876309],"iteration":430,"passed_time":0.8016915805,"remaining_time":0.1283450558},
{"learn":[5.969052922],"iteration":431,"passed_time":0.8038604767,"remaining_time":0.1265335936},
{"learn":[5.966741628],"iteration":432,"passed_time":0.8053416073,"remaining_time":0.1246140593},
{"learn":[5.963760934],"iteration":433,"passed_time":0.8074638709,"remaining_time":0.1227940449},
{"learn":[5.961435545],"iteration":434,"passed_time":0.81146925,"remaining_time":0.1212540259},
{"learn":[5.958588229],"iteration":435,"passed_time":0.8138592798,"remaining_time":0.1194655824},
{"learn":[5.95626621],"iteration":436,"passed_time":0.8155537194,"remaining_time":0.117574106},
{"learn":[5.953550074],"iteration":437,"passed_time":0.8170632807,"remaining_time":0.1156573594},
{"learn":[5.952008918],"iteration":438,"passed_time":0.8185996902,"remaining_time":0.1137461984},
{"learn":[5.949767991],"iteration":439,"passed_time":0.8202167334,"remaining_time":0.1118477364},
{"learn":[5.947693395],"iteration":440,"passed_time":0.8217811777,"remaining_time":0.1099435136},
{"learn":[5.944613456],"iteration":441,"passed_time":0.8250388379,"remaining_time":0.1082630149},
{"learn":[5.942341755],"iteration":442,"passed_time":0.8269662526,"remaining_time":0.1064042357},
{"learn":[5.940139006],"iteration":443,"passed_time":0.8284786978,"remaining_time":0.1044928087},
{"learn":[5.937989143],"iteration":444,"passed_time":0.8301114735,"remaining_time":0.1025980473},
{"learn":[5.935531474],"iteration":445,"passed_time":0.8315498443,"remaining_time":0.1006809228},
{"learn":[5.933112618],"iteration":446,"passed_time":0.8331244593,"remaining_time":0.09878209473},
{"learn":[5.930522714],"iteration":447,"passed_time":0.8346603021,"remaining_time":0.09688021364},
{"learn":[5.928447869],"iteration":448,"passed_time":0.8361616419,"remaining_time":0.09497604396},
{"learn":[5.926530424],"iteration":449,"passed_time":0.8382001043,"remaining_time":0.09313334492},
{"learn":[5.924408429],"iteration":450,"passed_time":0.8406891297,"remaining_time":0.09133873027},
{"learn":[5.922333455],"iteration":451,"passed_time":0.842766078,"remaining_time":0.08949728262},
{"learn":[5.920670084],"iteration":452,"passed_time":0.8442710592,"remaining_time":0.08759545206},
{"learn":[5.918197532],"iteration":453,"passed_time":0.8457563756,"remaining_time":0.08569337727},
{"learn":[5.916601072],"iteration":454,"passed_time":0.8473292828,"remaining_time":0.0838017972},
{"learn":[5.914996871],"iteration":455,"passed_time":0.8487757871,"remaining_time":0.08189941806},
{"learn":[5.912481196],"iteration":456,"passed_time":0.8502516953,"remaining_time":0.08000180065},
{"learn":[5.910458247],"iteration":457,"passed_time":0.8518139854,"remaining_time":0.07811394626},
{"learn":[5.908423829],"iteration":458,"passed_time":0.8545069201,"remaining_time":0.07632850484},
{"learn":[5.906087117],"iteration":459,"passed_time":0.8565849303,"remaining_time":0.07448564611},
{"learn":[5.903842442],"iteration":460,"passed_time":0.8586742298,"remaining_time":0.07264272226},
{"learn":[5.90175809],"iteration":461,"passed_time":0.860443648,"remaining_time":0.07077242126},
{"learn":[5.899784991],"iteration":462,"passed_time":0.8619079207,"remaining_time":0.06887817077},
{"learn":[5.89802327],"iteration":463,"passed_time":0.8634238093,"remaining_time":0.0669897783},
{"learn":[5.896450392],"iteration":464,"passed_time":0.8648569205,"remaining_time":0.06509675746},
{"learn":[5.894613177],"iteration":465,"passed_time":0.8664827355,"remaining_time":0.0632197704},
{"learn":[5.892908761],"iteration":466,"passed_time":0.8679436305,"remaining_time":0.06133220515},
{"learn":[5.890964701],"iteration":467,"passed_time":0.8707125155,"remaining_time":0.05953589849},
{"learn":[5.889000229],"iteration":468,"passed_time":0.8723396348,"remaining_time":0.05765997586},
{"learn":[5.887067821],"iteration":469,"passed_time":0.8738751632,"remaining_time":0.05577926573},
{"learn":[5.884920273],"iteration":470,"passed_time":0.8753512466,"remaining_time":0.05389636126},
{"learn":[5.882018055],"iteration":471,"passed_time":0.8768695394,"remaining_time":0.05201768454},
{"learn":[5.880465118],"iteration":472,"passed_time":0.8784324366,"remaining_time":0.05014307778},
{"learn":[5.878615519],"iteration":473,"passed_time":0.8798876489,"remaining_time":0.04826387947},
{"learn":[5.876702265],"iteration":474,"passed_time":0.881400808,"remaining_time":0.04638951621},
{"learn":[5.875164079],"iteration":475,"passed_time":0.8828532913,"remaining_time":0.04451361133},
{"learn":[5.873484065],"iteration":476,"passed_time":0.8852770141,"remaining_time":0.04268631305},
{"learn":[5.871450986],"iteration":477,"passed_time":0.8870438786,"remaining_time":0.0408262873},
{"learn":[5.86909134],"iteration":478,"passed_time":0.8884663674,"remaining_time":0.03895155264},
{"learn":[5.867722426],"iteration":479,"passed_time":0.8899705649,"remaining_time":0.03708210687},
{"learn":[5.865657535],"iteration":480,"passed_time":0.8915083801,"remaining_time":0.03521550774},
{"learn":[5.863581646],"iteration":481,"passed_time":0.892936297,"remaining_time":0.03334616877},
{"learn":[5.862069513],"iteration":482,"passed_time":0.8946067595,"remaining_time":0.03148719443},
{"learn":[5.860200067],"iteration":483,"passed_time":0.8961078411,"remaining_time":0.02962339971},
{"learn":[5.858304037],"iteration":484,"passed_time":0.8975790269,"remaining_time":0.02776017609},
{"learn":[5.856942418],"iteration":485,"passed_time":0.8991615064,"remaining_time":0.02590177179},
{"learn":[5.85440177],"iteration":486,"passed_time":0.9014381261,"remaining_time":0.02406303006},
{"learn":[5.852624123],"iteration":487,"passed_time":0.9029973733,"remaining_time":0.02220485344},
{"learn":[5.850230991],"iteration":488,"passed_time":0.904641913,"remaining_time":0.02034981808},
{"learn":[5.84850609],"iteration":489,"passed_time":0.9061891013,"remaining_time":0.01849365513},
{"learn":[5.846799085],"iteration":490,"passed_time":0.9077383132,"remaining_time":0.01663878782},
{"learn":[5.84485256],"iteration":491,"passed_time":0.9092320694,"remaining_time":0.01478426129},
{"learn":[5.842897748],"iteration":492,"passed_time":0.9108664244,"remaining_time":0.01293319467},
{"learn":[5.841588388],"iteration":493,"passed_time":0.9123739153,"remaining_time":0.01108146456},
{"learn":[5.839779099],"iteration":494,"passed_time":0.9140305353,"remaining_time":0.00923263167},
{"learn":[5.838342049],"iteration":495,"passed_time":0.9165189446,"remaining_time":0.007391281811},
{"learn":[5.836171133],"iteration":496,"passed_time":0.9181594307,"remaining_time":0.005542209843},
{"learn":[5.833276739],"iteration":497,"passed_time":0.9196422338,"remaining_time":0.003693342304},
{"learn":[5.831232018],"iteration":498,"passed_time":0.9212240872,"remaining_time":0.001846140455},
{"learn":[5.829493643],"iteration":499,"passed_time":0.9228554631,"remaining_time":0}
]}